CHANGELOG.txt
LICENSE.txt
MANIFEST.in
README.md
setup.py
StoaCalculator.egg-info/PKG-INFO
StoaCalculator.egg-info/SOURCES.txt
StoaCalculator.egg-info/dependency_links.txt
StoaCalculator.egg-info/requires.txt
StoaCalculator.egg-info/top_level.txt
stoacalculator/__init__.py