Metadata-Version: 2.1
Name: StoaCalculator
Version: 1.1.0
Summary: Stoa Calculator is a powerful calculator that have everything you need to do any kind of calculations!
Author: Jorge Eldis Gonzalez
Author-email: jorgeeldisg30@gmail.com
License: MIT
Project-URL: Documentation, https://pypi.org/project/StoaCalculator/
Project-URL: Say Thanks!, https://saythanks.io/to/jorgeeldis
Project-URL: Source, https://github.com/jorgeeldis/StoaCalculator
Project-URL: Tracker, https://github.com/jorgeeldis/StoaCalculator/issues
Keywords: calculator education algebra calculus trigonometry arithmetic university
Platform: UNKNOWN
Classifier: Development Status :: 5 - Production/Stable
Classifier: Intended Audience :: Education
Classifier: Environment :: Console
Classifier: Framework :: IPython
Classifier: Natural Language :: English
Classifier: Topic :: Education
Classifier: Operating System :: Microsoft :: Windows :: Windows 10
Classifier: License :: OSI Approved :: MIT License
Classifier: Programming Language :: Python :: 3
Classifier: Programming Language :: Python :: 3.6
Classifier: Programming Language :: Python :: 3.7
Classifier: Programming Language :: Python :: 3.8
Classifier: Programming Language :: Python :: 3.9
Requires-Python: >=3
License-File: LICENSE.txt
